rand_num_gen_with_json/__init__.py
rand_num_gen_with_json/randNumGenWithJson.py
image_with_rand_number-0.0.1.dist-info/LICENSE
image_with_rand_number-0.0.1.dist-info/METADATA
image_with_rand_number-0.0.1.dist-info/WHEEL
image_with_rand_number-0.0.1.dist-info/top_level.txt
image_with_rand_number-0.0.1.dist-info/RECORD
