Metadata-Version: 2.1
Name: image-with-rand-number
Version: 0.0.1
Summary: A small package for make an image with printed random number
Home-page: https://github.com/pypa/imagewithrandnumproject
Author: Shah Arfan Mahdi
Author-email: shahmahdi11@gmail.com
License: UNKNOWN
Project-URL: Bug Tracker, https://github.com/pypa/imagewithrandnumproject/issues
Platform: UNKNOWN
Classifier: Programming Language :: Python :: 3
Classifier: License :: OSI Approved :: MIT License
Classifier: Operating System :: OS Independent
Requires-Python: >=2.7
License-File: LICENSE
